LICENSE
MANIFEST.in
README
README.rst
setup.py
django_throttling/__init__.py
django_throttling/middleware.py
django_throttling/models.py
django_throttling/settings.py
django_throttling/tests.py
django_throttling/util.py
django_throttling/views.py
django_throttling.egg-info/PKG-INFO
django_throttling.egg-info/SOURCES.txt
django_throttling.egg-info/dependency_links.txt
django_throttling.egg-info/top_level.txt