Metadata-Version: 1.1
Name: django-throttling
Version: 0.0.1
Summary: Basic throttling app for Django
Home-page: http://github.com/night-crawler/django-throttling
Author: Igor
Author-email: lilo.panic@gmail.com
License: MIT
Keywords: django,throttling
Platform: UNKNOWN
Classifier: Development Status :: 2 - Pre-Alpha
Classifier: Environment :: Web Environment
Classifier: Framework :: Django
Classifier: Intended Audience :: Developers
Classifier: Intended Audience :: Information Technology
Classifier: Intended Audience :: System Administrators
Classifier: License :: OSI Approved :: MIT License
Classifier: Natural Language :: English
Classifier: Operating System :: OS Independent
Classifier: Programming Language :: Python
Classifier: Topic :: Internet :: WWW/HTTP :: Dynamic Content :: Page Counters
Classifier: Topic :: Internet :: WWW/HTTP :: WSGI :: Middleware
Classifier: Topic :: Security
Classifier: Topic :: Utilities
